{"nodes": [{"id": "agent_plan_lonetolkaren", "label": "L\u00f6netolkaren \u2014 AO Parser & App Overview", "file_type": "document", "source_file": "AGENT_PLAN.md", "source_location": null, "source_url": null, "captured_at": null, "author": null, "contributor": null}, {"id": "agent_plan_ao_parser", "label": "AO Parser (parseAoWorkbook.ts)", "file_type": "concept", "source_file": "AGENT_PLAN.md", "source_location": "line 8", "source_url": null, "captured_at": null, "author": null, "contributor": null}, {"id": "agent_plan_vinter_ao", "label": "Vinter-AO File Type", "file_type": "concept", "source_file": "AGENT_PLAN.md", "source_location": "line 15", "source_url": null, "captured_at": null, "author": null, "contributor": null}, {"id": "agent_plan_var_host_ao", "label": "V\u00e5r/h\u00f6st-AO File Type", "file_type": "concept", "source_file": "AGENT_PLAN.md", "source_location": "line 112", "source_url": null, "captured_at": null, "author": null, "contributor": null}, {"id": "agent_plan_detectmode", "label": "detectMode() \u2014 AO block mode detection", "file_type": "concept", "source_file": "AGENT_PLAN.md", "source_location": "line 65", "source_url": null, "captured_at": null, "author": null, "contributor": null}, {"id": "agent_plan_extractmeta", "label": "extractMeta() \u2014 AO meta extraction", "file_type": "concept", "source_file": "AGENT_PLAN.md", "source_location": "line 124", "source_url": null, "captured_at": null, "author": null, "contributor": null}, {"id": "agent_plan_extractallperiods", "label": "extractAllPeriods() \u2014 multi-period regex", "file_type": "concept", "source_file": "AGENT_PLAN.md", "source_location": "line 139", "source_url": null, "captured_at": null, "author": null, "contributor": null}, {"id": "agent_plan_blockcoverstdate", "label": "blockCoversDate() \u2014 date coverage check", "file_type": "concept", "source_file": "AGENT_PLAN.md", "source_location": "line 148", "source_url": null, "captured_at": null, "author": null, "contributor": null}, {"id": "agent_plan_getaofordate", "label": "getAoForDate() \u2014 block lookup by date", "file_type": "concept", "source_file": "AGENT_PLAN.md", "source_location": "line 261", "source_url": null, "captured_at": null, "author": null, "contributor": null}, {"id": "agent_plan_calculatemonthylsalary", "label": "calculateMonthlySalary() \u2014 wage calculation", "file_type": "concept", "source_file": "AGENT_PLAN.md", "source_location": "line 263", "source_url": null, "captured_at": null, "author": null, "contributor": null}, {"id": "agent_plan_workcalendar", "label": "WorkCalendar Component", "file_type": "concept", "source_file": "AGENT_PLAN.md", "source_location": "line 249", "source_url": null, "captured_at": null, "author": null, "contributor": null}, {"id": "agent_plan_daymodal", "label": "DayModal Component", "file_type": "concept", "source_file": "AGENT_PLAN.md", "source_location": "line 250", "source_url": null, "captured_at": null, "author": null, "contributor": null}, {"id": "agent_plan_tariffeditor", "label": "TariffEditor Component", "file_type": "concept", "source_file": "AGENT_PLAN.md", "source_location": "line 251", "source_url": null, "captured_at": null, "author": null, "contributor": null}, {"id": "agent_plan_loneberakningcontext", "label": "LoneberakningContext \u2014 shared state", "file_type": "concept", "source_file": "AGENT_PLAN.md", "source_location": "line 252", "source_url": null, "captured_at": null, "author": null, "contributor": null}, {"id": "agent_plan_aoupload", "label": "AoUpload Component", "file_type": "concept", "source_file": "AGENT_PLAN.md", "source_location": "line 253", "source_url": null, "captured_at": null, "author": null, "contributor": null}, {"id": "agent_plan_boatselect", "label": "BoatSelect Component", "file_type": "concept", "source_file": "AGENT_PLAN.md", "source_location": "line 254", "source_url": null, "captured_at": null, "author": null, "contributor": null}, {"id": "agent_plan_aoblock", "label": "AoBlock \u2014 block data structure", "file_type": "concept", "source_file": "AGENT_PLAN.md", "source_location": "line 256", "source_url": null, "captured_at": null, "author": null, "contributor": null}, {"id": "agent_plan_parsedaosheet", "label": "ParsedAoSheet \u2014 sheet data structure", "file_type": "concept", "source_file": "AGENT_PLAN.md", "source_location": "line 256", "source_url": null, "captured_at": null, "author": null, "contributor": null}, {"id": "agent_plan_loadparsedaosheet", "label": "loadParsedAoSheet() \u2014 backward compat loader", "file_type": "concept", "source_file": "AGENT_PLAN.md", "source_location": "line 209", "source_url": null, "captured_at": null, "author": null, "contributor": null}, {"id": "agent_plan_skargardsavtalet", "label": "Sk\u00e4rg\u00e5rdsavtalet 2025-2027 \u2014 collective agreement", "file_type": "concept", "source_file": "AGENT_PLAN.md", "source_location": "line 219", "source_url": null, "captured_at": null, "author": null, "contributor": null}, {"id": "agent_plan_ob_calculation", "label": "OB Calculation Rules (\u00a77 Sk\u00e4rg\u00e5rdsavtalet)", "file_type": "rationale", "source_file": "AGENT_PLAN.md", "source_location": "line 272", "source_url": null, "captured_at": null, "author": null, "contributor": null}, {"id": "agent_plan_overtime_calculation", "label": "Overtime Calculation Rules (\u00a76.3)", "file_type": "rationale", "source_file": "AGENT_PLAN.md", "source_location": "line 280", "source_url": null, "captured_at": null, "author": null, "contributor": null}, {"id": "agent_plan_hourly_rate", "label": "Hourly Rate Rules (\u00a711.2 + Bilaga 1)", "file_type": "rationale", "source_file": "AGENT_PLAN.md", "source_location": "line 284", "source_url": null, "captured_at": null, "author": null, "contributor": null}, {"id": "agent_plan_savedmonth", "label": "SavedMonth \u2014 monthly persistence data structure", "file_type": "concept", "source_file": "AGENT_PLAN.md", "source_location": "line 362", "source_url": null, "captured_at": null, "author": null, "contributor": null}, {"id": "agent_plan_namdo_problem", "label": "N\u00e4md\u00f6 mixed ice mode problem", "file_type": "rationale", "source_file": "AGENT_PLAN.md", "source_location": "line 319", "source_url": null, "captured_at": null, "author": null, "contributor": null}, {"id": "agent_plan_sommarluckan", "label": "Summer gap \u2014 no AO data for July", "file_type": "concept", "source_file": "AGENT_PLAN.md", "source_location": "line 184", "source_url": null, "captured_at": null, "author": null, "contributor": null}, {"id": "agent_plan_crewindex", "label": "crewIndex \u2014 multi-crew indexing", "file_type": "concept", "source_file": "AGENT_PLAN.md", "source_location": "line 88", "source_url": null, "captured_at": null, "author": null, "contributor": null}, {"id": "agent_plan_hasIsVariant", "label": "hasIsVariant \u2014 ice mode flag", "file_type": "concept", "source_file": "AGENT_PLAN.md", "source_location": "line 43", "source_url": null, "captured_at": null, "author": null, "contributor": null}], "edges": [{"source": "agent_plan_ao_parser", "target": "agent_plan_vinter_ao", "relation": "references", "confidence": "EXTRACTED", "confidence_score": 1.0, "source_file": "AGENT_PLAN.md", "source_location": "line 15", "weight": 1.0}, {"source": "agent_plan_ao_parser", "target": "agent_plan_var_host_ao", "relation": "references", "confidence": "EXTRACTED", "confidence_score": 1.0, "source_file": "AGENT_PLAN.md", "source_location": "line 112", "weight": 1.0}, {"source": "agent_plan_ao_parser", "target": "agent_plan_detectmode", "relation": "references", "confidence": "EXTRACTED", "confidence_score": 1.0, "source_file": "AGENT_PLAN.md", "source_location": "line 65", "weight": 1.0}, {"source": "agent_plan_ao_parser", "target": "agent_plan_extractmeta", "relation": "references", "confidence": "EXTRACTED", "confidence_score": 1.0, "source_file": "AGENT_PLAN.md", "source_location": "line 124", "weight": 1.0}, {"source": "agent_plan_extractmeta", "target": "agent_plan_extractallperiods", "relation": "references", "confidence": "EXTRACTED", "confidence_score": 1.0, "source_file": "AGENT_PLAN.md", "source_location": "line 127", "weight": 1.0}, {"source": "agent_plan_getaofordate", "target": "agent_plan_blockcoverstdate", "relation": "references", "confidence": "EXTRACTED", "confidence_score": 1.0, "source_file": "AGENT_PLAN.md", "source_location": "line 148", "weight": 1.0}, {"source": "agent_plan_blockcoverstdate", "target": "agent_plan_var_host_ao", "relation": "conceptually_related_to", "confidence": "EXTRACTED", "confidence_score": 1.0, "source_file": "AGENT_PLAN.md", "source_location": "line 148", "weight": 1.0}, {"source": "agent_plan_ao_parser", "target": "agent_plan_aoblock", "relation": "references", "confidence": "EXTRACTED", "confidence_score": 1.0, "source_file": "AGENT_PLAN.md", "source_location": "line 256", "weight": 1.0}, {"source": "agent_plan_ao_parser", "target": "agent_plan_parsedaosheet", "relation": "references", "confidence": "EXTRACTED", "confidence_score": 1.0, "source_file": "AGENT_PLAN.md", "source_location": "line 256", "weight": 1.0}, {"source": "agent_plan_aoblock", "target": "agent_plan_crewindex", "relation": "references", "confidence": "EXTRACTED", "confidence_score": 1.0, "source_file": "AGENT_PLAN.md", "source_location": "line 309", "weight": 1.0}, {"source": "agent_plan_aoblock", "target": "agent_plan_hasIsVariant", "relation": "references", "confidence": "INFERRED", "confidence_score": 0.95, "source_file": "AGENT_PLAN.md", "source_location": "line 43", "weight": 1.0}, {"source": "agent_plan_parsedaosheet", "target": "agent_plan_hasIsVariant", "relation": "references", "confidence": "EXTRACTED", "confidence_score": 1.0, "source_file": "AGENT_PLAN.md", "source_location": "line 312", "weight": 1.0}, {"source": "agent_plan_loadparsedaosheet", "target": "agent_plan_parsedaosheet", "relation": "references", "confidence": "EXTRACTED", "confidence_score": 1.0, "source_file": "AGENT_PLAN.md", "source_location": "line 209", "weight": 1.0}, {"source": "agent_plan_detectmode", "target": "agent_plan_namdo_problem", "relation": "rationale_for", "confidence": "EXTRACTED", "confidence_score": 1.0, "source_file": "AGENT_PLAN.md", "source_location": "line 65", "weight": 1.0}, {"source": "agent_plan_calculatemonthylsalary", "target": "agent_plan_ob_calculation", "relation": "references", "confidence": "EXTRACTED", "confidence_score": 1.0, "source_file": "AGENT_PLAN.md", "source_location": "line 272", "weight": 1.0}, {"source": "agent_plan_calculatemonthylsalary", "target": "agent_plan_overtime_calculation", "relation": "references", "confidence": "EXTRACTED", "confidence_score": 1.0, "source_file": "AGENT_PLAN.md", "source_location": "line 280", "weight": 1.0}, {"source": "agent_plan_calculatemonthylsalary", "target": "agent_plan_hourly_rate", "relation": "references", "confidence": "EXTRACTED", "confidence_score": 1.0, "source_file": "AGENT_PLAN.md", "source_location": "line 284", "weight": 1.0}, {"source": "agent_plan_ob_calculation", "target": "agent_plan_skargardsavtalet", "relation": "references", "confidence": "EXTRACTED", "confidence_score": 1.0, "source_file": "AGENT_PLAN.md", "source_location": "line 272", "weight": 1.0}, {"source": "agent_plan_overtime_calculation", "target": "agent_plan_skargardsavtalet", "relation": "references", "confidence": "EXTRACTED", "confidence_score": 1.0, "source_file": "AGENT_PLAN.md", "source_location": "line 280", "weight": 1.0}, {"source": "agent_plan_hourly_rate", "target": "agent_plan_skargardsavtalet", "relation": "references", "confidence": "EXTRACTED", "confidence_score": 1.0, "source_file": "AGENT_PLAN.md", "source_location": "line 284", "weight": 1.0}, {"source": "agent_plan_workcalendar", "target": "agent_plan_savedmonth", "relation": "references", "confidence": "EXTRACTED", "confidence_score": 1.0, "source_file": "AGENT_PLAN.md", "source_location": "line 353", "weight": 1.0}, {"source": "agent_plan_workcalendar", "target": "agent_plan_calculatemonthylsalary", "relation": "references", "confidence": "EXTRACTED", "confidence_score": 1.0, "source_file": "AGENT_PLAN.md", "source_location": "line 263", "weight": 1.0}, {"source": "agent_plan_workcalendar", "target": "agent_plan_getaofordate", "relation": "references", "confidence": "INFERRED", "confidence_score": 0.95, "source_file": "AGENT_PLAN.md", "source_location": "line 261", "weight": 1.0}, {"source": "agent_plan_getaofordate", "target": "agent_plan_sommarluckan", "relation": "conceptually_related_to", "confidence": "EXTRACTED", "confidence_score": 1.0, "source_file": "AGENT_PLAN.md", "source_location": "line 184", "weight": 1.0}, {"source": "agent_plan_var_host_ao", "target": "agent_plan_sommarluckan", "relation": "conceptually_related_to", "confidence": "EXTRACTED", "confidence_score": 1.0, "source_file": "AGENT_PLAN.md", "source_location": "line 185", "weight": 1.0}, {"source": "agent_plan_lonetolkaren", "target": "agent_plan_skargardsavtalet", "relation": "references", "confidence": "EXTRACTED", "confidence_score": 1.0, "source_file": "AGENT_PLAN.md", "source_location": "line 219", "weight": 1.0}, {"source": "agent_plan_lonetolkaren", "target": "agent_plan_ao_parser", "relation": "references", "confidence": "EXTRACTED", "confidence_score": 1.0, "source_file": "AGENT_PLAN.md", "source_location": "line 8", "weight": 1.0}, {"source": "agent_plan_lonetolkaren", "target": "agent_plan_workcalendar", "relation": "references", "confidence": "EXTRACTED", "confidence_score": 1.0, "source_file": "AGENT_PLAN.md", "source_location": "line 249", "weight": 1.0}, {"source": "agent_plan_lonetolkaren", "target": "agent_plan_calculatemonthylsalary", "relation": "references", "confidence": "EXTRACTED", "confidence_score": 1.0, "source_file": "AGENT_PLAN.md", "source_location": "line 263", "weight": 1.0}, {"source": "agent_plan_lonetolkaren", "target": "readme_nextjs", "relation": "references", "confidence": "INFERRED", "confidence_score": 0.95, "source_file": "AGENT_PLAN.md", "source_location": "line 219", "weight": 1.0}, {"source": "skargardstrafik_pdf", "target": "agent_plan_skargardsavtalet", "relation": "references", "confidence": "EXTRACTED", "confidence_score": 1.0, "source_file": "AGENT_PLAN.md", "source_location": "line 405", "weight": 1.0}, {"source": "agent_plan_skargardsavtalet", "target": "skargardstrafik_pdf", "relation": "references", "confidence": "EXTRACTED", "confidence_score": 1.0, "source_file": "AGENT_PLAN.md", "source_location": "line 405", "weight": 1.0}, {"source": "agent_plan_extractallperiods", "target": "agent_plan_var_host_ao", "relation": "rationale_for", "confidence": "INFERRED", "confidence_score": 0.95, "source_file": "AGENT_PLAN.md", "source_location": "line 139", "weight": 1.0}, {"source": "agent_plan_detectmode", "target": "agent_plan_vinter_ao", "relation": "conceptually_related_to", "confidence": "INFERRED", "confidence_score": 0.85, "source_file": "AGENT_PLAN.md", "source_location": "line 65", "weight": 1.0}], "hyperedges": [{"id": "ao_block_fields_hyperedge", "label": "AoBlock extended fields \u2014 crewIndex, modeExplicit, extraPeriods, hasIsVariant", "nodes": ["agent_plan_crewindex", "agent_plan_hasIsVariant", "agent_plan_aoblock", "agent_plan_parsedaosheet"], "relation": "participate_in", "confidence": "EXTRACTED", "confidence_score": 0.95, "source_file": "AGENT_PLAN.md"}, {"id": "salary_calculation_rules", "label": "Wage calculation rules from Sk\u00e4rg\u00e5rdsavtalet implemented in calculateMonthlySalary", "nodes": ["agent_plan_ob_calculation", "agent_plan_overtime_calculation", "agent_plan_hourly_rate", "agent_plan_calculatemonthylsalary", "agent_plan_skargardsavtalet"], "relation": "implement", "confidence": "EXTRACTED", "confidence_score": 1.0, "source_file": "AGENT_PLAN.md"}]}